{
    "help": "https://ckan.publishing.service.gov.uk/api/3/action/help_show?name=package_show",
    "success": true,
    "result": {
        "codelist": "",
        "contact-email": "",
        "contact-name": "",
        "contact-phone": "",
        "creator_user_id": "0ff4d4fc-96c6-475a-9949-f2c469f7b501",
        "foi-email": "",
        "foi-name": "",
        "foi-phone": "",
        "foi-web": "",
        "id": "f9ddf832-83c5-4df2-96db-f1567f6ab1ab",
        "isopen": true,
        "licence-custom": "",
        "license_id": "uk-ogl",
        "license_title": "UK Open Government Licence (OGL)",
        "license_url": "http://reference.data.gov.uk/id/open-government-licence",
        "metadata_created": "2016-08-01T12:45:25.149044",
        "metadata_modified": "2019-03-26T09:32:18.350233",
        "name": "deaths-registered-by-area-in-england-and-wales-monthly-provisional-and-monthly-annual",
        "notes": "Number of deaths registered in a calendar month, by area of usual residence.",
        "num_resources": 16,
        "num_tags": 0,
        "organization": {
            "id": "d5b50862-3f2a-4b7b-ad85-841b6def43be",
            "name": "office-for-national-statistics",
            "title": "Office for National Statistics",
            "type": "organization",
            "description": "The Office for National Statistics (ONS) is the UK\u2019s largest independent producer of official statistics and is the recognised national statistical institute for the UK. It is responsible for collecting and publishing statistics related to the economy, population and society at national, regional and local levels. It also conducts the census in England and Wales every ten years. \r\n\r\nThe ONS plays a leading role in national and international good practice in the production of official statistics. It is the executive office of the UK Statistics Authority and although they are separate, they are still closely related.\r\n",
            "image_url": "",
            "created": "2012-06-27T14:48:40.553767",
            "is_organization": true,
            "approval_status": "pending",
            "state": "active"
        },
        "owner_org": "d5b50862-3f2a-4b7b-ad85-841b6def43be",
        "private": false,
        "schema-vocabulary": "",
        "state": "active",
        "theme-primary": "society",
        "title": "Deaths registered by area in England and Wales, monthly provisional and monthly annual",
        "type": "dataset",
        "url": null,
        "version": null,
        "resources": [
            {
                "cache_last_updated": null,
                "cache_url": null,
                "created": "2016-08-01T13:45:25.208979",
                "description": "Deaths registered by area in England and Wales, monthly provisional: June 2016 and monthly annual: 2015 (final)",
                "format": "HTML",
                "hash": "",
                "id": "9f48e446-8495-4420-838a-684095a67088",
                "last_modified": null,
                "metadata_modified": "2016-08-01T13:45:25.208979",
                "mimetype": null,
                "mimetype_inner": null,
                "name": null,
                "package_id": "f9ddf832-83c5-4df2-96db-f1567f6ab1ab",
                "position": 0,
                "resource_type": "file",
                "size": null,
                "state": "active",
                "url": "https://www.ons.gov.uk/releases/monthlyfiguresondeathsregisteredbyareaofusualresidenceenglandandwalesjune2016provisional",
                "url_type": null
            },
            {
                "cache_last_updated": null,
                "cache_url": null,
                "created": "2016-11-22T09:49:37.501491",
                "description": "Deaths registered by area in England and Wales, monthly provisional: Oct 2016",
                "format": "HTML",
                "hash": "",
                "id": "9bd19f51-b0b4-4604-8261-5f453c6841ef",
                "last_modified": null,
                "metadata_modified": "2016-11-22T09:49:37.501491",
                "mimetype": null,
                "mimetype_inner": null,
                "name": null,
                "package_id": "f9ddf832-83c5-4df2-96db-f1567f6ab1ab",
                "position": 1,
                "resource_type": "file",
                "size": null,
                "state": "active",
                "url": "https://www.ons.gov.uk/releases/deathsregisteredbyareainenglandandwalesmonthlyprovisionaloct2016",
                "url_type": null
            },
            {
                "cache_last_updated": null,
                "cache_url": null,
                "created": "2017-01-10T09:41:34.665085",
                "description": "Deaths registered by area in England and Wales, monthly provisional: Nov 2016",
                "format": "HTML",
                "hash": "",
                "id": "5aff08d9-5102-4609-9e1f-2420290fd5d9",
                "last_modified": null,
                "metadata_modified": "2017-01-10T09:41:34.665085",
                "mimetype": null,
                "mimetype_inner": null,
                "name": null,
                "package_id": "f9ddf832-83c5-4df2-96db-f1567f6ab1ab",
                "position": 2,
                "resource_type": "file",
                "size": null,
                "state": "active",
                "url": "https://www.ons.gov.uk/releases/deathsregisteredbyareainenglandandwalesmonthlyprovisionalnov2016",
                "url_type": null
            },
            {
                "cache_last_updated": null,
                "cache_url": null,
                "created": "2017-01-25T09:50:14.828974",
                "description": "Deaths registered by area in England and Wales, monthly provisional: Dec 2016",
                "format": "HTML ",
                "hash": "",
                "id": "bed2e935-a44d-480a-92ab-0df563cac271",
                "last_modified": null,
                "metadata_modified": "2017-01-25T09:50:14.828974",
                "mimetype": null,
                "mimetype_inner": null,
                "name": null,
                "package_id": "f9ddf832-83c5-4df2-96db-f1567f6ab1ab",
                "position": 3,
                "resource_type": "file",
                "size": null,
                "state": "active",
                "url": "https://www.ons.gov.uk/peoplepopulationandcommunity/birthsdeathsandmarriages/deaths/datasets/monthlyfiguresondeathsregisteredbyareaofusualresidence",
                "url_type": null
            },
            {
                "cache_last_updated": null,
                "cache_url": null,
                "created": "2017-02-28T09:59:49.999093",
                "description": "Deaths registered by area in England and Wales, monthly provisional: Jan 2017",
                "format": "HTML",
                "hash": "",
                "id": "25e5f012-7183-4279-b537-cbf6078e5864",
                "last_modified": null,
                "metadata_modified": "2017-02-28T09:59:49.999093",
                "mimetype": null,
                "mimetype_inner": null,
                "name": null,
                "package_id": "f9ddf832-83c5-4df2-96db-f1567f6ab1ab",
                "position": 4,
                "resource_type": "file",
                "size": null,
                "state": "active",
                "url": "https://www.ons.gov.uk/releases/deathsregisteredbyareainenglandandwalesmonthlyprovisionaljan2017",
                "url_type": null
            },
            {
                "cache_last_updated": null,
                "cache_url": null,
                "created": "2017-03-28T11:26:27.653158",
                "description": "Deaths registered by area in England and Wales, monthly provisional: Feb 2017",
                "format": "HTML",
                "hash": "",
                "id": "27582bd6-15a2-44e7-8b7e-2fe8f0589c86",
                "last_modified": null,
                "metadata_modified": "2017-03-28T11:26:27.653158",
                "mimetype": null,
                "mimetype_inner": null,
                "name": null,
                "package_id": "f9ddf832-83c5-4df2-96db-f1567f6ab1ab",
                "position": 5,
                "resource_type": "file",
                "size": null,
                "state": "active",
                "url": "https://www.ons.gov.uk/releases/deathsregisteredbyareainenglandandwalesmonthlyprovisionalfeb2017",
                "url_type": null
            },
            {
                "cache_last_updated": null,
                "cache_url": null,
                "created": "2017-04-26T12:08:38.784628",
                "description": "Deaths registered by area in England and Wales, monthly provisional: Mar 2017",
                "format": "HTML",
                "hash": "",
                "id": "3214b6c9-7e19-46fd-9df4-72113d08b61b",
                "last_modified": null,
                "metadata_modified": "2017-04-26T12:08:38.784628",
                "mimetype": null,
                "mimetype_inner": null,
                "name": null,
                "package_id": "f9ddf832-83c5-4df2-96db-f1567f6ab1ab",
                "position": 6,
                "resource_type": "file",
                "size": null,
                "state": "active",
                "url": "https://www.ons.gov.uk/releases/deathsregisteredbyareainenglandandwalesmonthlyprovisionalmar2017",
                "url_type": null
            },
            {
                "cache_last_updated": null,
                "cache_url": null,
                "created": "2017-08-22T09:32:43.214267",
                "description": "Deaths registered by area in England and Wales, monthly provisional: July 2017",
                "format": "HTML",
                "hash": "",
                "id": "1f303ee5-6d97-4e5b-b36d-85ae2c99f86c",
                "last_modified": null,
                "metadata_modified": "2017-08-22T09:32:43.214267",
                "mimetype": null,
                "mimetype_inner": null,
                "name": null,
                "package_id": "f9ddf832-83c5-4df2-96db-f1567f6ab1ab",
                "position": 7,
                "resource_type": "file",
                "size": null,
                "state": "active",
                "url": "https://www.ons.gov.uk/releases/deathsregisteredbyareainenglandandwalesmonthlyprovisionaljuly2017",
                "url_type": null
            },
            {
                "cache_last_updated": null,
                "cache_url": null,
                "created": "2017-10-26T12:10:09.738914",
                "description": "Deaths registered by area in England and Wales, monthly provisional: Sept 2017",
                "format": "HTML",
                "hash": "",
                "id": "e4c0a8a9-5288-4dc8-94a4-3ab043f3dd8b",
                "last_modified": null,
                "metadata_modified": "2017-10-26T12:10:09.738914",
                "mimetype": null,
                "mimetype_inner": null,
                "name": null,
                "package_id": "f9ddf832-83c5-4df2-96db-f1567f6ab1ab",
                "position": 8,
                "resource_type": "file",
                "size": null,
                "state": "active",
                "url": "https://www.ons.gov.uk/releases/deathsregisteredbyareainenglandandwalesmonthlyprovisionalsept2017",
                "url_type": null
            },
            {
                "cache_last_updated": null,
                "cache_url": null,
                "created": "2018-01-09T09:37:02.039876",
                "description": "Deaths registered by area of usual residence in England and Wales: November 2017",
                "format": "HTML",
                "hash": "",
                "id": "cc5612cb-56e3-4021-ad6b-a1ad15e79548",
                "last_modified": null,
                "metadata_modified": "2018-01-09T09:37:02.039876",
                "mimetype": null,
                "mimetype_inner": null,
                "name": null,
                "package_id": "f9ddf832-83c5-4df2-96db-f1567f6ab1ab",
                "position": 9,
                "resource_type": "file",
                "size": null,
                "state": "active",
                "url": "https://www.ons.gov.uk/peoplepopulationandcommunity/birthsdeathsandmarriages/deaths/datasets/monthlyfiguresondeathsregisteredbyareaofusualresidence",
                "url_type": null
            },
            {
                "cache_last_updated": null,
                "cache_url": null,
                "created": "2018-02-28T10:14:36.736855",
                "description": "Deaths registered by area in England and Wales, monthly provisional: January 2018",
                "format": "HTML",
                "hash": "",
                "id": "ccf98fb3-00f4-4bc2-aa60-8e1b0376ec1c",
                "last_modified": null,
                "metadata_modified": "2018-02-28T10:14:36.736855",
                "mimetype": null,
                "mimetype_inner": null,
                "name": null,
                "package_id": "f9ddf832-83c5-4df2-96db-f1567f6ab1ab",
                "position": 10,
                "resource_type": "file",
                "size": null,
                "state": "active",
                "url": "https://www.ons.gov.uk/releases/deathsregisteredbyareainenglandandwalesmonthlyprovisionaljan2018",
                "url_type": null
            },
            {
                "cache_last_updated": null,
                "cache_url": null,
                "created": "2018-03-27T09:50:49.199413",
                "description": "Deaths registered by area in England and Wales, monthly provisional: February 2018",
                "format": "HTML",
                "hash": "",
                "id": "57c546be-a256-455a-a081-d3b7e5aaa099",
                "last_modified": null,
                "metadata_modified": "2018-03-27T09:50:49.199413",
                "mimetype": null,
                "mimetype_inner": null,
                "name": null,
                "package_id": "f9ddf832-83c5-4df2-96db-f1567f6ab1ab",
                "position": 11,
                "resource_type": "file",
                "size": null,
                "state": "active",
                "url": "https://www.ons.gov.uk/peoplepopulationandcommunity/birthsdeathsandmarriages/deaths/datasets/monthlyfiguresondeathsregisteredbyareaofusualresidence",
                "url_type": null
            },
            {
                "cache_last_updated": null,
                "cache_url": null,
                "created": "2018-06-26T09:34:48.849409",
                "description": "Deaths registered monthly in England and Wales: May 2018",
                "format": "HTML",
                "hash": "",
                "id": "a84e1e70-4986-4788-9a47-de5b42c5db64",
                "last_modified": null,
                "metadata_modified": "2018-06-26T09:34:48.849409",
                "mimetype": null,
                "mimetype_inner": null,
                "name": null,
                "package_id": "f9ddf832-83c5-4df2-96db-f1567f6ab1ab",
                "position": 12,
                "resource_type": "file",
                "size": null,
                "state": "active",
                "url": "https://www.ons.gov.uk/releases/deathsregisteredbyareainenglandandwalesmonthlyprovisionalmay2018",
                "url_type": null
            },
            {
                "cache_last_updated": null,
                "cache_url": null,
                "created": "2018-08-29T09:41:25.871752",
                "description": "Deaths registered monthly in England and Wales: July 2018",
                "format": "HTML",
                "hash": "",
                "id": "5e303201-4116-456e-a461-a9769c4451f5",
                "last_modified": null,
                "metadata_modified": "2018-08-29T09:41:25.871752",
                "mimetype": null,
                "mimetype_inner": null,
                "name": null,
                "package_id": "f9ddf832-83c5-4df2-96db-f1567f6ab1ab",
                "position": 13,
                "resource_type": "file",
                "size": null,
                "state": "active",
                "url": "https://www.ons.gov.uk/releases/deathsregisteredbyareainenglandandwalesmonthlyprovisionaljuly2018",
                "url_type": null
            },
            {
                "cache_last_updated": null,
                "cache_url": null,
                "created": "2019-02-27T09:19:50.874071",
                "datafile-date": "26 February 2019",
                "description": "",
                "format": "HTML",
                "hash": "",
                "id": "4017fb3b-6ad6-48de-b4aa-fc00b1f3ee9c",
                "last_modified": null,
                "metadata_modified": "2019-02-27T09:19:50.874071",
                "mimetype": null,
                "mimetype_inner": null,
                "name": "Deaths registered monthly in England and Wales: January 2019",
                "package_id": "f9ddf832-83c5-4df2-96db-f1567f6ab1ab",
                "position": 14,
                "resource-type": "data-link",
                "resource_type": null,
                "size": null,
                "state": "active",
                "url": "https://www.ons.gov.uk/releases/deathsregisteredbyareainenglandandwalesmonthlyprovisionaljanuary2019",
                "url_type": null
            },
            {
                "cache_last_updated": null,
                "cache_url": null,
                "created": "2019-03-26T09:32:18.514233",
                "datafile-date": "26 March 2019",
                "description": "",
                "format": "HTML",
                "hash": "",
                "id": "fa09c8a7-9578-47d8-9c94-f9f765d68785",
                "last_modified": null,
                "metadata_modified": "2019-03-26T09:32:18.514233",
                "mimetype": null,
                "mimetype_inner": null,
                "name": "Deaths registered monthly in England and Wales: February 2019",
                "package_id": "f9ddf832-83c5-4df2-96db-f1567f6ab1ab",
                "position": 15,
                "resource-type": "data-link",
                "resource_type": null,
                "size": null,
                "state": "active",
                "url": "https://www.ons.gov.uk/releases/deathsregisteredbyareainenglandandwalesmonthlyprovisionalfebruary2019",
                "url_type": null
            }
        ],
        "tags": [],
        "groups": [],
        "relationships_as_subject": [],
        "relationships_as_object": []
    }
}