{
    "help": "https://ckan.publishing.service.gov.uk/api/3/action/help_show?name=package_show",
    "success": true,
    "result": {
        "contact-email": "",
        "contact-name": "",
        "contact-phone": "",
        "core-dataset": false,
        "creator_user_id": "ab19a913-1fd8-4ec6-9595-cb579a9fd0b2",
        "date_released": "2001-04-06",
        "date_updated": "2014-07-25",
        "foi-email": "",
        "foi-name": "",
        "foi-phone": "",
        "foi-web": "",
        "geographic_coverage": "111100: United Kingdom (England, Scotland, Wales, Northern Ireland)",
        "geographic_granularity": "UK and GB",
        "id": "465adedf-48aa-4dc0-a250-a060c3946711",
        "isopen": true,
        "license_id": "uk-ogl",
        "license_title": "UK Open Government Licence (OGL)",
        "license_url": "http://reference.data.gov.uk/id/open-government-licence",
        "metadata_created": "2011-12-10T19:14:31.982523",
        "metadata_modified": "2018-11-09T09:42:28.816386",
        "name": "gross_domestic_product-preliminary_estimate",
        "notes": "Preliminary estimate for Gross Domestic Product (GDP) containing constant price Gross Value Added (GVA) data for the UK. Data are available by industrial sector.\r\nSource agency: Office for National Statistics\r\nDesignation: National Statistics\r\nLanguage: English\r\nAlternative title: Gross Domestic Product: Preliminary Estimate",
        "num_resources": 46,
        "num_tags": 0,
        "odi-certificate": {
            "status": "final",
            "source": "Automatically awarded by ODI",
            "certification_type": "automatically awarded",
            "level": "bronze",
            "title": "Gross Domestic Product: Preliminary Estimate",
            "created_at": "2014-10-29T14:29:09Z",
            "jurisdiction": "GB",
            "certificate_url": "https://certificates.theodi.org/en/datasets/8487/certificate",
            "badge_url": "https://certificates.theodi.org/en/datasets/8487/certificate/badge.png",
            "cert_title": "Bronze level certificate"
        },
        "organization": {
            "id": "d5b50862-3f2a-4b7b-ad85-841b6def43be",
            "name": "office-for-national-statistics",
            "title": "Office for National Statistics",
            "type": "organization",
            "description": "The Office for National Statistics (ONS) is the UK\u2019s largest independent producer of official statistics and is the recognised national statistical institute for the UK. It is responsible for collecting and publishing statistics related to the economy, population and society at national, regional and local levels. It also conducts the census in England and Wales every ten years. \r\n\r\nThe ONS plays a leading role in national and international good practice in the production of official statistics. It is the executive office of the UK Statistics Authority and although they are separate, they are still closely related.\r\n",
            "image_url": "",
            "created": "2012-06-27T14:48:40.553767",
            "is_organization": true,
            "approval_status": "pending",
            "state": "active"
        },
        "owner_org": "d5b50862-3f2a-4b7b-ad85-841b6def43be",
        "private": false,
        "state": "active",
        "temporal_coverage-from": "",
        "temporal_coverage-to": "",
        "theme-primary": "business-and-economy",
        "theme-secondary": [
            ""
        ],
        "title": "Gross Domestic Product: Preliminary Estimate",
        "type": "dataset",
        "unpublished": false,
        "update_frequency": "",
        "url": null,
        "version": null,
        "extras": [
            {
                "key": "categories",
                "value": "Economy"
            },
            {
                "key": "external_reference",
                "value": "ONSHUB"
            },
            {
                "key": "geographical_granularity",
                "value": "UK and GB"
            },
            {
                "key": "import_source",
                "value": "ONS-ons_data_1_days_to_2014-07-25"
            },
            {
                "key": "its-dataset",
                "value": "false"
            },
            {
                "key": "national_statistic",
                "value": "yes"
            },
            {
                "key": "register",
                "value": "false"
            },
            {
                "key": "series",
                "value": "Gross Domestic Product: Preliminary Estimate"
            },
            {
                "key": "sla",
                "value": ""
            }
        ],
        "resources": [
            {
                "cache_last_updated": null,
                "cache_url": null,
                "description": "Revisions Data: Household Savings Ratio",
                "format": "HTML",
                "hub-id": "77-52604",
                "id": "7f232ef6-4421-4060-9373-1134677ec295",
                "last_modified": null,
                "metadata_modified": null,
                "mimetype": null,
                "mimetype_inner": null,
                "name": null,
                "package_id": "465adedf-48aa-4dc0-a250-a060c3946711",
                "position": 0,
                "resource_type": "file",
                "size": null,
                "state": "active",
                "url": "http://webarchive.nationalarchives.gov.uk/+/http://www.ons.gov.uk/ons/dcp19975_52604.xml",
                "url_type": null
            },
            {
                "cache_last_updated": null,
                "cache_url": null,
                "description": "Revisions Data: Components of Output measure",
                "format": "HTML",
                "hub-id": "77-52606",
                "id": "bf962b1a-850f-4993-9f99-5ee2ede7f805",
                "last_modified": null,
                "metadata_modified": null,
                "mimetype": null,
                "mimetype_inner": null,
                "name": null,
                "package_id": "465adedf-48aa-4dc0-a250-a060c3946711",
                "position": 1,
                "resource_type": "file",
                "size": null,
                "state": "active",
                "url": "http://webarchive.nationalarchives.gov.uk/+/http://www.ons.gov.uk/ons/dcp19975_52606.xml",
                "url_type": null
            },
            {
                "cache_last_updated": null,
                "cache_url": null,
                "description": "UK Price and Volume (ESA95) Inventory",
                "format": "HTML",
                "hub-id": "77-52771",
                "id": "5015c476-dd76-4391-aaef-18da32ddd55f",
                "last_modified": null,
                "metadata_modified": null,
                "mimetype": null,
                "mimetype_inner": null,
                "name": null,
                "package_id": "465adedf-48aa-4dc0-a250-a060c3946711",
                "position": 2,
                "resource_type": "file",
                "size": null,
                "state": "active",
                "url": "http://webarchive.nationalarchives.gov.uk/+/http://www.ons.gov.uk/ons/dcp19975_52771.xml",
                "url_type": null
            },
            {
                "cache_last_updated": null,
                "cache_url": null,
                "created": "2013-03-11T16:25:37.813216",
                "description": "Q1 2009",
                "format": "HTML",
                "hub-id": "77-217047",
                "id": "4db42bda-651d-4426-8627-1b53c4c5eaa7",
                "last_modified": null,
                "metadata_modified": "2013-03-11T16:25:37.813216",
                "mimetype": null,
                "mimetype_inner": null,
                "name": null,
                "package_id": "465adedf-48aa-4dc0-a250-a060c3946711",
                "position": 3,
                "publish-date": "2009-04-24",
                "resource_type": "file",
                "size": null,
                "state": "active",
                "url": "http://www.ons.gov.uk/ons/dcp19975_217047.xml",
                "url_type": null
            },
            {
                "cache_last_updated": null,
                "cache_url": null,
                "created": "2013-03-11T17:08:03.686916",
                "description": "Q2 2009",
                "format": "HTML",
                "hub-id": "77-217074",
                "id": "5d0a4f9f-5c0f-4953-81fc-8ef29bfbc4e9",
                "last_modified": null,
                "metadata_modified": "2013-03-11T17:08:03.686916",
                "mimetype": null,
                "mimetype_inner": null,
                "name": null,
                "package_id": "465adedf-48aa-4dc0-a250-a060c3946711",
                "position": 4,
                "publish-date": "2009-07-24",
                "resource_type": "file",
                "size": null,
                "state": "active",
                "url": "http://www.ons.gov.uk/ons/dcp19975_217074.xml",
                "url_type": null
            },
            {
                "cache_last_updated": null,
                "cache_url": null,
                "created": "2013-03-11T18:02:43.821803",
                "description": "Q3 2009",
                "format": "HTML",
                "hub-id": "77-217110",
                "id": "254390f7-528a-46a5-8fc9-15abc7ecaeb7",
                "last_modified": null,
                "metadata_modified": "2013-03-11T18:02:43.821803",
                "mimetype": null,
                "mimetype_inner": null,
                "name": null,
                "package_id": "465adedf-48aa-4dc0-a250-a060c3946711",
                "position": 5,
                "publish-date": "2009-10-26",
                "resource_type": "file",
                "size": null,
                "state": "active",
                "url": "http://www.ons.gov.uk/ons/dcp19975_217110.xml",
                "url_type": null
            },
            {
                "cache_last_updated": null,
                "cache_url": null,
                "created": "2013-03-11T18:21:14.440915",
                "description": "Understanding the quality of early estimates of Gross Domestic Product",
                "format": "HTML",
                "hub-id": "77-52602",
                "id": "a21ba32a-c0d5-44e4-b959-3d50439380a4",
                "last_modified": null,
                "metadata_modified": "2013-03-11T18:21:14.440915",
                "mimetype": null,
                "mimetype_inner": null,
                "name": null,
                "package_id": "465adedf-48aa-4dc0-a250-a060c3946711",
                "position": 6,
                "publish-date": "2009-11-25",
                "resource_type": "file",
                "size": null,
                "state": "active",
                "url": "http://www.ons.gov.uk/ons/dcp19975_52602.xml",
                "url_type": null
            },
            {
                "cache_last_updated": null,
                "cache_url": null,
                "created": "2013-03-11T18:56:07.199000",
                "description": "Q4 2009",
                "format": "HTML",
                "hub-id": "77-217090",
                "id": "ea99bbe6-45b1-4579-a9f7-cf7701485e09",
                "last_modified": null,
                "metadata_modified": "2013-03-11T18:56:07.199000",
                "mimetype": null,
                "mimetype_inner": null,
                "name": null,
                "package_id": "465adedf-48aa-4dc0-a250-a060c3946711",
                "position": 7,
                "publish-date": "2010-01-25",
                "resource_type": "file",
                "size": null,
                "state": "active",
                "url": "http://www.ons.gov.uk/ons/dcp19975_217090.xml",
                "url_type": null
            },
            {
                "cache_last_updated": null,
                "cache_url": null,
                "created": "2013-03-11T19:53:00.945195",
                "description": "Q1 2010",
                "format": "HTML",
                "hub-id": "77-217062",
                "id": "ebfd4f8d-a64d-4886-9c45-7053dae98ca7",
                "last_modified": null,
                "metadata_modified": "2013-03-11T19:53:00.945195",
                "mimetype": null,
                "mimetype_inner": null,
                "name": null,
                "package_id": "465adedf-48aa-4dc0-a250-a060c3946711",
                "position": 8,
                "publish-date": "2010-04-23",
                "resource_type": "file",
                "size": null,
                "state": "active",
                "url": "http://www.ons.gov.uk/ons/dcp19975_217062.xml",
                "url_type": null
            },
            {
                "cache_last_updated": null,
                "cache_url": null,
                "created": "2013-03-11T20:54:50.318279",
                "description": "Q2 2010",
                "format": "HTML",
                "hub-id": "77-217055",
                "id": "7a219e18-3f4f-4049-8b36-1086f0541269",
                "last_modified": null,
                "metadata_modified": "2013-03-11T20:54:50.318279",
                "mimetype": null,
                "mimetype_inner": null,
                "name": null,
                "package_id": "465adedf-48aa-4dc0-a250-a060c3946711",
                "position": 9,
                "publish-date": "2010-07-23",
                "resource_type": "file",
                "size": null,
                "state": "active",
                "url": "http://www.ons.gov.uk/ons/dcp19975_217055.xml",
                "url_type": null
            },
            {
                "cache_last_updated": null,
                "cache_url": null,
                "created": "2013-03-11T21:58:19.567430",
                "description": "Q3 2010",
                "format": "HTML",
                "hub-id": "77-29098",
                "id": "631a5288-3141-4fbd-91fc-75741f1b8487",
                "last_modified": null,
                "metadata_modified": "2013-03-11T21:58:19.567430",
                "mimetype": null,
                "mimetype_inner": null,
                "name": null,
                "package_id": "465adedf-48aa-4dc0-a250-a060c3946711",
                "position": 10,
                "publish-date": "2010-10-26",
                "resource_type": "file",
                "size": null,
                "state": "active",
                "url": "http://www.ons.gov.uk/ons/dcp19975_29098.xml",
                "url_type": null
            },
            {
                "cache_last_updated": null,
                "cache_url": null,
                "created": "2013-03-11T22:56:54.006974",
                "description": "Q4 2010",
                "format": "HTML",
                "hub-id": "77-198939",
                "id": "a5e123f6-3aba-4574-8c2f-599cc7efcd62",
                "last_modified": null,
                "metadata_modified": "2013-03-11T22:56:54.006974",
                "mimetype": null,
                "mimetype_inner": null,
                "name": null,
                "package_id": "465adedf-48aa-4dc0-a250-a060c3946711",
                "position": 11,
                "publish-date": "2011-01-25",
                "resource_type": "file",
                "size": null,
                "state": "active",
                "url": "http://www.ons.gov.uk/ons/dcp19975_198939.xml",
                "url_type": null
            },
            {
                "cache_last_updated": null,
                "cache_url": null,
                "created": "2013-03-11T23:58:37.463774",
                "description": "Q1 2011",
                "format": "HTML",
                "hub-id": "77-216553",
                "id": "53b1fd86-0e73-441a-838c-c335570a7b2b",
                "last_modified": null,
                "metadata_modified": "2013-03-11T23:58:37.463774",
                "mimetype": null,
                "mimetype_inner": null,
                "name": null,
                "package_id": "465adedf-48aa-4dc0-a250-a060c3946711",
                "position": 12,
                "publish-date": "2011-04-27",
                "resource_type": "file",
                "size": null,
                "state": "active",
                "url": "http://www.ons.gov.uk/ons/dcp19975_216553.xml",
                "url_type": null
            },
            {
                "cache_last_updated": null,
                "cache_url": null,
                "created": "2013-03-12T01:02:10.919404",
                "description": "Q2 2011",
                "format": "HTML",
                "hub-id": "77-224031",
                "id": "71d4df63-c674-4ff8-9131-fff0c175282f",
                "last_modified": null,
                "metadata_modified": "2013-03-12T01:02:10.919404",
                "mimetype": null,
                "mimetype_inner": null,
                "name": null,
                "package_id": "465adedf-48aa-4dc0-a250-a060c3946711",
                "position": 13,
                "publish-date": "2011-07-26",
                "resource_type": "file",
                "size": null,
                "state": "active",
                "url": "http://www.ons.gov.uk/ons/dcp19975_224031.xml",
                "url_type": null
            },
            {
                "cache_last_updated": null,
                "cache_url": null,
                "created": "2013-03-12T02:21:18.783125",
                "description": "Q3 2011",
                "format": "HTML",
                "hub-id": "77-222646",
                "id": "3505f207-86b5-419a-b27f-c2c51b05991e",
                "last_modified": null,
                "metadata_modified": "2013-03-12T02:21:18.783125",
                "mimetype": null,
                "mimetype_inner": null,
                "name": null,
                "package_id": "465adedf-48aa-4dc0-a250-a060c3946711",
                "position": 14,
                "publish-date": "2011-11-01",
                "resource_type": "file",
                "size": null,
                "state": "active",
                "url": "http://www.ons.gov.uk/ons/dcp19975_222646.xml",
                "url_type": null
            },
            {
                "cache_last_updated": null,
                "cache_url": null,
                "created": "2013-10-01T01:07:53.700343",
                "description": "Q4 2011",
                "format": "HTML",
                "hub-id": "77-230787",
                "id": "7f3b8240-0ae5-492b-8b0c-be49af28bf3d",
                "last_modified": null,
                "metadata_modified": "2013-10-01T01:07:53.700343",
                "mimetype": null,
                "mimetype_inner": null,
                "name": null,
                "package_id": "465adedf-48aa-4dc0-a250-a060c3946711",
                "position": 15,
                "publish-date": "2012-01-25",
                "resource_type": "file",
                "size": null,
                "state": "active",
                "url": "http://www.ons.gov.uk/ons/dcp19975_230787.xml",
                "url_type": null
            },
            {
                "cache_last_updated": null,
                "cache_url": null,
                "created": "2013-03-12T04:31:13.542338",
                "description": "Q1 2012",
                "format": "HTML",
                "hub-id": "77-230791",
                "id": "047364fb-401e-47ec-b7cc-e63d9791328c",
                "last_modified": null,
                "metadata_modified": "2013-03-12T04:31:13.542338",
                "mimetype": null,
                "mimetype_inner": null,
                "name": null,
                "package_id": "465adedf-48aa-4dc0-a250-a060c3946711",
                "position": 16,
                "publish-date": "2012-04-25",
                "resource_type": "file",
                "size": null,
                "state": "active",
                "url": "http://www.ons.gov.uk/ons/dcp19975_230791.xml",
                "url_type": null
            },
            {
                "cache_last_updated": null,
                "cache_url": null,
                "created": "2013-10-01T02:12:51.659750",
                "description": "Statistical Special Events In Quarter Two 2012",
                "format": "HTML",
                "hub-id": "77-273990",
                "id": "711697b2-1a03-4b54-90e0-7effee1c74cd",
                "last_modified": null,
                "metadata_modified": "2013-10-01T02:12:51.659750",
                "mimetype": null,
                "mimetype_inner": null,
                "name": null,
                "package_id": "465adedf-48aa-4dc0-a250-a060c3946711",
                "position": 17,
                "publish-date": "2012-07-25",
                "resource_type": "file",
                "size": null,
                "state": "active",
                "url": "http://www.ons.gov.uk/ons/dcp19975_273990.xml",
                "url_type": null
            },
            {
                "cache_last_updated": null,
                "cache_url": null,
                "created": "2013-10-01T02:13:04.022164",
                "description": "Q2 2012",
                "format": "HTML",
                "hub-id": "77-230797",
                "id": "71317c8c-84d6-48b1-82e9-25424bad5764",
                "last_modified": null,
                "metadata_modified": "2013-10-01T02:13:04.022164",
                "mimetype": null,
                "mimetype_inner": null,
                "name": null,
                "package_id": "465adedf-48aa-4dc0-a250-a060c3946711",
                "position": 18,
                "publish-date": "2012-07-25",
                "resource_type": "file",
                "size": null,
                "state": "active",
                "url": "http://www.ons.gov.uk/ons/dcp19975_230797.xml",
                "url_type": null
            },
            {
                "cache_last_updated": null,
                "cache_url": null,
                "created": "2013-10-01T02:47:44.729718",
                "description": "Continuous Improvement in the measurement of Gross Domestic Product",
                "format": "HTML",
                "hub-id": "77-283889",
                "id": "65320004-effd-403f-8905-55b8274e9861",
                "last_modified": null,
                "metadata_modified": "2013-10-01T02:47:44.729718",
                "mimetype": null,
                "mimetype_inner": null,
                "name": null,
                "package_id": "465adedf-48aa-4dc0-a250-a060c3946711",
                "position": 19,
                "publish-date": "2012-10-24",
                "resource_type": "file",
                "size": null,
                "state": "active",
                "url": "http://www.ons.gov.uk/ons/dcp19975_283889.xml",
                "url_type": null
            },
            {
                "cache_last_updated": null,
                "cache_url": null,
                "created": "2013-10-01T02:48:29.502892",
                "description": "Statistical Special Events in Quarter Three 2012 - the Olympics and Paralympics",
                "format": "HTML",
                "hub-id": "77-283539",
                "id": "a0fa765c-e3ac-4f51-9e7e-1afce506ec76",
                "last_modified": null,
                "metadata_modified": "2013-10-01T02:48:29.502892",
                "mimetype": null,
                "mimetype_inner": null,
                "name": null,
                "package_id": "465adedf-48aa-4dc0-a250-a060c3946711",
                "position": 20,
                "publish-date": "2012-10-25",
                "resource_type": "file",
                "size": null,
                "state": "active",
                "url": "http://www.ons.gov.uk/ons/dcp19975_283539.xml",
                "url_type": null
            },
            {
                "cache_last_updated": null,
                "cache_url": null,
                "created": "2013-10-01T02:48:41.389826",
                "description": "Q3 2012",
                "format": "HTML",
                "hub-id": "77-230799",
                "id": "1e9737a1-6ac9-45c4-b364-d5d4a8e4fd2c",
                "last_modified": null,
                "metadata_modified": "2013-10-01T02:48:41.389826",
                "mimetype": null,
                "mimetype_inner": null,
                "name": null,
                "package_id": "465adedf-48aa-4dc0-a250-a060c3946711",
                "position": 21,
                "publish-date": "2012-10-25",
                "resource_type": "file",
                "size": null,
                "state": "active",
                "url": "http://www.ons.gov.uk/ons/dcp19975_230799.xml",
                "url_type": null
            },
            {
                "cache_last_updated": null,
                "cache_url": null,
                "created": "2013-10-01T03:19:03.858303",
                "description": "Q4 2012",
                "format": "HTML",
                "hub-id": "77-264767",
                "id": "f6fea03f-94d4-43b5-bfd4-29cdb4c9b375",
                "last_modified": null,
                "metadata_modified": "2013-10-01T03:19:03.858303",
                "mimetype": null,
                "mimetype_inner": null,
                "name": null,
                "package_id": "465adedf-48aa-4dc0-a250-a060c3946711",
                "position": 22,
                "publish-date": "2013-01-25",
                "resource_type": "file",
                "size": null,
                "state": "active",
                "url": "http://www.ons.gov.uk/ons/dcp19975_264767.xml",
                "url_type": null
            },
            {
                "cache_last_updated": null,
                "cache_url": null,
                "created": "2013-03-08T01:53:25.263996",
                "description": "Understanding & Interpreting the Q4 2012 Gross Domestic Product Preliminary Estimate",
                "format": "HTML",
                "hub-id": "77-295558",
                "id": "7ed44d44-4385-4f5a-9947-04f1c828db4b",
                "last_modified": null,
                "metadata_modified": "2013-03-08T01:53:25.263996",
                "mimetype": null,
                "mimetype_inner": null,
                "name": null,
                "package_id": "465adedf-48aa-4dc0-a250-a060c3946711",
                "position": 23,
                "publish-date": "2013-01-25",
                "resource_type": "file",
                "size": null,
                "state": "active",
                "url": "http://www.ons.gov.uk/ons/dcp19975_295558.xml",
                "url_type": null
            },
            {
                "cache_last_updated": null,
                "cache_url": null,
                "created": "2013-04-24T09:40:56.571459",
                "description": "GDP Continuous Improvement: progress update",
                "format": "HTML",
                "hub-id": "77-300992",
                "id": "2b2babfd-cb86-4e44-b4a6-cc4759f63d84",
                "last_modified": null,
                "metadata_modified": "2013-04-24T09:40:56.571459",
                "mimetype": null,
                "mimetype_inner": null,
                "name": null,
                "package_id": "465adedf-48aa-4dc0-a250-a060c3946711",
                "position": 24,
                "publish-date": "2013-04-24",
                "resource_type": "file",
                "size": null,
                "state": "active",
                "url": "http://www.ons.gov.uk/ons/dcp19975_300992.xml",
                "url_type": null
            },
            {
                "cache_last_updated": null,
                "cache_url": null,
                "created": "2013-04-25T09:41:26.645224",
                "description": "Q1 2013",
                "format": "HTML",
                "hub-id": "77-264791",
                "id": "03c6cb1a-a16a-4de0-b762-d81cb1648a5c",
                "last_modified": null,
                "metadata_modified": "2013-04-25T09:41:26.645224",
                "mimetype": null,
                "mimetype_inner": null,
                "name": null,
                "package_id": "465adedf-48aa-4dc0-a250-a060c3946711",
                "position": 25,
                "publish-date": "2013-04-25",
                "resource_type": "file",
                "size": null,
                "state": "active",
                "url": "http://www.ons.gov.uk/ons/dcp19975_264791.xml",
                "url_type": null
            },
            {
                "cache_last_updated": null,
                "cache_url": null,
                "created": "2013-07-25T09:41:14.170936",
                "description": "Q2 2013",
                "format": "HTML",
                "hub-id": "77-265226",
                "id": "2effcf2b-a748-4bbf-8a8a-59fbdb3684de",
                "last_modified": null,
                "metadata_modified": "2013-07-25T09:41:14.170936",
                "mimetype": null,
                "mimetype_inner": null,
                "name": null,
                "package_id": "465adedf-48aa-4dc0-a250-a060c3946711",
                "position": 26,
                "publish-date": "2013-07-25",
                "resource_type": "file",
                "size": null,
                "state": "active",
                "url": "http://www.ons.gov.uk/ons/dcp19975_265226.xml",
                "url_type": null
            },
            {
                "cache_last_updated": null,
                "cache_url": null,
                "created": "2013-12-16T14:18:12.121005",
                "description": "Q3 2013",
                "format": "HTML",
                "hub-id": "77-265230",
                "id": "9e4fb583-f532-405c-9479-1a8c9c35274e",
                "last_modified": null,
                "metadata_modified": "2013-12-16T14:18:12.121005",
                "mimetype": null,
                "mimetype_inner": null,
                "name": null,
                "package_id": "465adedf-48aa-4dc0-a250-a060c3946711",
                "position": 27,
                "publish-date": "2013-10-25",
                "resource_type": "file",
                "size": null,
                "state": "active",
                "url": "http://www.ons.gov.uk/ons/dcp19975_265230.xml",
                "url_type": null
            },
            {
                "cache_last_updated": null,
                "cache_url": null,
                "created": "2014-01-28T09:40:30.391761",
                "description": "Q4 2013",
                "format": "HTML",
                "hub-id": "77-304189",
                "id": "9ad699d4-f904-48c1-9a24-99ff9fb0e807",
                "last_modified": null,
                "metadata_modified": "2014-01-28T09:40:30.391761",
                "mimetype": null,
                "mimetype_inner": null,
                "name": null,
                "package_id": "465adedf-48aa-4dc0-a250-a060c3946711",
                "position": 28,
                "publish-date": "2014-01-28",
                "resource_type": "file",
                "size": null,
                "state": "active",
                "url": "http://www.ons.gov.uk/ons/dcp19975_304189.xml",
                "url_type": null
            },
            {
                "cache_last_updated": null,
                "cache_url": null,
                "created": "2014-04-29T09:40:21.814289",
                "description": "Q1 2014",
                "format": "HTML",
                "hub-id": "77-304191",
                "id": "3d01adaa-a684-4374-bbdc-22370bd38a38",
                "last_modified": null,
                "metadata_modified": "2014-04-29T09:40:21.814289",
                "mimetype": null,
                "mimetype_inner": null,
                "name": null,
                "package_id": "465adedf-48aa-4dc0-a250-a060c3946711",
                "position": 29,
                "publish-date": "2014-04-29",
                "resource_type": "file",
                "size": null,
                "state": "active",
                "url": "http://www.ons.gov.uk/ons/dcp19975_304191.xml",
                "url_type": null
            },
            {
                "cache_last_updated": null,
                "cache_url": null,
                "created": "2014-05-29T12:00:02.893490",
                "description": "Continuous Improvement of Gross Domestic Product - May 2014",
                "format": "HTML",
                "hash": "",
                "hub-id": "77-357410",
                "id": "64229f65-571e-4fcb-8dfa-82ad48ae41c8",
                "last_modified": null,
                "metadata_modified": "2014-05-29T12:00:02.893490",
                "mimetype": null,
                "mimetype_inner": null,
                "name": null,
                "package_id": "465adedf-48aa-4dc0-a250-a060c3946711",
                "position": 30,
                "publish-date": "2014-05-29",
                "resource_type": "file",
                "size": null,
                "state": "active",
                "url": "http://www.ons.gov.uk/ons/dcp19975_357410.xml",
                "url_type": null
            },
            {
                "cache_last_updated": null,
                "cache_url": null,
                "created": "2014-07-25T09:40:18.982450",
                "description": "Q2 2014",
                "format": "HTML",
                "hash": "",
                "hub-id": "77-304193",
                "id": "eff22039-879d-4dff-a945-655813c009b3",
                "last_modified": null,
                "metadata_modified": "2014-07-25T09:40:18.982450",
                "mimetype": null,
                "mimetype_inner": null,
                "name": null,
                "package_id": "465adedf-48aa-4dc0-a250-a060c3946711",
                "position": 31,
                "publish-date": "2014-07-25",
                "resource_type": "file",
                "size": null,
                "state": "active",
                "url": "http://www.ons.gov.uk/ons/dcp19975_304193.xml",
                "url_type": null
            },
            {
                "cache_last_updated": null,
                "cache_url": null,
                "created": "2014-10-24T11:16:25.274780",
                "description": "Q3 2014",
                "format": "HTML",
                "hash": "",
                "id": "5525a921-f096-4f8b-aefb-85dd0056fa4f",
                "last_modified": null,
                "metadata_modified": "2014-10-24T11:16:25.274780",
                "mimetype": null,
                "mimetype_inner": null,
                "name": null,
                "package_id": "465adedf-48aa-4dc0-a250-a060c3946711",
                "position": 32,
                "resource_type": "file",
                "size": null,
                "state": "active",
                "url": "http://www.ons.gov.uk/ons/rel/gva/gross-domestic-product--preliminary-estimate/q3-2014/index.html",
                "url_type": null
            },
            {
                "cache_last_updated": null,
                "cache_url": null,
                "created": "2015-01-28T15:17:10.252767",
                "description": "Q4 2014",
                "format": "HTML",
                "hash": "",
                "id": "8713d522-0bfc-44bf-b04d-58adc00ea300",
                "last_modified": null,
                "metadata_modified": "2015-01-28T15:17:10.252767",
                "mimetype": null,
                "mimetype_inner": null,
                "name": null,
                "package_id": "465adedf-48aa-4dc0-a250-a060c3946711",
                "position": 33,
                "resource_type": "file",
                "size": null,
                "state": "active",
                "url": "http://www.ons.gov.uk/ons/rel/gva/gross-domestic-product--preliminary-estimate/q4-2014/index.html",
                "url_type": null
            },
            {
                "cache_last_updated": null,
                "cache_url": null,
                "created": "2015-05-01T11:25:09.112845",
                "description": "Q1 2015",
                "format": "HTML",
                "hash": "",
                "id": "9a736839-10f7-41aa-8f28-208c4fb09b32",
                "last_modified": null,
                "metadata_modified": "2015-05-01T11:25:09.112845",
                "mimetype": null,
                "mimetype_inner": null,
                "name": null,
                "package_id": "465adedf-48aa-4dc0-a250-a060c3946711",
                "position": 34,
                "resource_type": "file",
                "size": null,
                "state": "active",
                "url": "http://www.ons.gov.uk/ons/rel/gva/gross-domestic-product--preliminary-estimate/q1-2015/index.html",
                "url_type": null
            },
            {
                "cache_last_updated": null,
                "cache_url": null,
                "created": "2015-10-02T09:08:54.388703",
                "description": "Q2 2015",
                "format": "HTML",
                "hash": "",
                "id": "b7331b79-99e9-4934-8968-5491a8a8e7ea",
                "last_modified": null,
                "metadata_modified": "2015-10-02T09:08:54.388703",
                "mimetype": null,
                "mimetype_inner": null,
                "name": null,
                "package_id": "465adedf-48aa-4dc0-a250-a060c3946711",
                "position": 35,
                "resource_type": "file",
                "size": null,
                "state": "active",
                "url": "http://www.ons.gov.uk/ons/rel/gva/gross-domestic-product--preliminary-estimate/q2-2015/index.html",
                "url_type": null
            },
            {
                "cache_last_updated": null,
                "cache_url": null,
                "created": "2015-10-27T12:51:09.223207",
                "description": "Quarter 3 (July to Sept) 2015",
                "format": "HTML",
                "hash": "",
                "id": "fcc766a2-0197-456f-a8e1-ca5056bc43a6",
                "last_modified": null,
                "metadata_modified": "2015-10-27T12:51:09.223207",
                "mimetype": null,
                "mimetype_inner": null,
                "name": null,
                "package_id": "465adedf-48aa-4dc0-a250-a060c3946711",
                "position": 36,
                "resource_type": "file",
                "size": null,
                "state": "active",
                "url": "http://www.ons.gov.uk/ons/rel/gva/gross-domestic-product--preliminary-estimate/q3-2015/index.html",
                "url_type": null
            },
            {
                "cache_last_updated": null,
                "cache_url": null,
                "created": "2016-01-28T11:55:24.088013",
                "description": "Quarter 4 (Oct to Dec) 2015",
                "format": "HTML",
                "hash": "",
                "id": "7fcf186e-f8fc-45d7-93a2-9e54019da487",
                "last_modified": null,
                "metadata_modified": "2016-01-28T11:55:24.088013",
                "mimetype": null,
                "mimetype_inner": null,
                "name": null,
                "package_id": "465adedf-48aa-4dc0-a250-a060c3946711",
                "position": 37,
                "resource_type": "file",
                "size": null,
                "state": "active",
                "url": "http://www.ons.gov.uk/ons/rel/gva/gross-domestic-product--preliminary-estimate/q4-2015/index.html",
                "url_type": null
            },
            {
                "cache_last_updated": null,
                "cache_url": null,
                "created": "2016-04-27T11:30:16.267913",
                "description": "Quarter 1 (Jan to Mar) 2016",
                "format": "HTML",
                "hash": "",
                "id": "3c2c9ce7-1b06-42ba-b4e2-9ef4a8bcfe54",
                "last_modified": null,
                "metadata_modified": "2016-04-27T11:30:16.267913",
                "mimetype": null,
                "mimetype_inner": null,
                "name": null,
                "package_id": "465adedf-48aa-4dc0-a250-a060c3946711",
                "position": 38,
                "resource_type": "file",
                "size": null,
                "state": "active",
                "url": "https://www.ons.gov.uk/releases/grossdomesticproductpreliminaryestimatejanuarytomarch2016",
                "url_type": null
            },
            {
                "cache_last_updated": null,
                "cache_url": null,
                "created": "2016-08-01T14:04:28.482730",
                "description": "Quarter 2 (Apr to June) 2016",
                "format": "HTML",
                "hash": "",
                "id": "fd7f5163-e100-4f7e-856e-ef39f89fbb1e",
                "last_modified": null,
                "metadata_modified": "2016-08-01T14:04:28.482730",
                "mimetype": null,
                "mimetype_inner": null,
                "name": null,
                "package_id": "465adedf-48aa-4dc0-a250-a060c3946711",
                "position": 39,
                "resource_type": "file",
                "size": null,
                "state": "active",
                "url": "https://www.ons.gov.uk/releases/grossdomesticproductpreliminaryestimateapriltojune2016",
                "url_type": null
            },
            {
                "cache_last_updated": null,
                "cache_url": null,
                "created": "2017-01-27T09:40:20.169673",
                "description": "Quarter 3 (July to Sept) 2016",
                "format": "HTML",
                "hash": "",
                "id": "0b29e996-645a-443a-b11b-37d91f2a2119",
                "last_modified": null,
                "metadata_modified": "2017-01-27T09:40:20.169673",
                "mimetype": null,
                "mimetype_inner": null,
                "name": null,
                "package_id": "465adedf-48aa-4dc0-a250-a060c3946711",
                "position": 40,
                "resource_type": "file",
                "size": null,
                "state": "active",
                "url": "https://www.ons.gov.uk/economy/grossdomesticproductgdp/bulletins/grossdomesticproductpreliminaryestimate/julytosept2016",
                "url_type": null
            },
            {
                "cache_last_updated": null,
                "cache_url": null,
                "created": "2017-01-27T09:40:20.169704",
                "description": "Quarter 4 (Oct to Dec) 2016",
                "format": "HTML",
                "hash": "",
                "id": "441fabf6-a604-4e24-bef4-e88990a6a11e",
                "last_modified": null,
                "metadata_modified": "2017-01-27T09:40:20.169704",
                "mimetype": null,
                "mimetype_inner": null,
                "name": null,
                "package_id": "465adedf-48aa-4dc0-a250-a060c3946711",
                "position": 41,
                "resource_type": "file",
                "size": null,
                "state": "active",
                "url": "https://www.ons.gov.uk/economy/grossdomesticproductgdp/bulletins/grossdomesticproductpreliminaryestimate/octtodec2016",
                "url_type": null
            },
            {
                "cache_last_updated": null,
                "cache_url": null,
                "created": "2017-10-26T12:14:11.043768",
                "description": "July to September 2017",
                "format": "HTML",
                "hash": "",
                "id": "554bab2a-e94e-4649-8751-d72a7ec9bdef",
                "last_modified": null,
                "metadata_modified": "2017-10-26T12:14:11.043768",
                "mimetype": null,
                "mimetype_inner": null,
                "name": null,
                "package_id": "465adedf-48aa-4dc0-a250-a060c3946711",
                "position": 42,
                "resource_type": "file",
                "size": null,
                "state": "active",
                "url": "https://www.ons.gov.uk/releases/ukgdppreliminaryestimatejulytosept2017",
                "url_type": null
            },
            {
                "cache_last_updated": null,
                "cache_url": null,
                "created": "2018-01-26T09:34:31.680953",
                "description": "October to December 2017",
                "format": "HTML",
                "hash": "",
                "id": "0eeca885-fb57-4398-bb86-69dc060b4ef5",
                "last_modified": null,
                "metadata_modified": "2018-01-26T09:34:31.680953",
                "mimetype": null,
                "mimetype_inner": null,
                "name": null,
                "package_id": "465adedf-48aa-4dc0-a250-a060c3946711",
                "position": 43,
                "resource_type": "file",
                "size": null,
                "state": "active",
                "url": "https://www.ons.gov.uk/releases/ukgdppreliminaryestimateocttodec2017",
                "url_type": null
            },
            {
                "cache_last_updated": null,
                "cache_url": null,
                "created": "2018-04-27T08:48:09.687674",
                "description": "January to March 2018",
                "format": "HTML",
                "hash": "",
                "id": "201feb5b-9286-413c-8176-f8e412369805",
                "last_modified": null,
                "metadata_modified": "2018-04-27T08:48:09.687674",
                "mimetype": null,
                "mimetype_inner": null,
                "name": null,
                "package_id": "465adedf-48aa-4dc0-a250-a060c3946711",
                "position": 44,
                "resource_type": "file",
                "size": null,
                "state": "active",
                "url": "https://www.ons.gov.uk/releases/ukgdppreliminaryestimatejantomar2018",
                "url_type": null
            },
            {
                "cache_last_updated": null,
                "cache_url": null,
                "created": "2018-11-09T09:42:28.965888",
                "description": "July to September 2018",
                "format": "HTML",
                "hash": "",
                "id": "4203c0e4-668c-4bb1-a9ad-bb1ae5039c30",
                "last_modified": null,
                "metadata_modified": "2018-11-09T09:42:28.965888",
                "mimetype": null,
                "mimetype_inner": null,
                "name": null,
                "package_id": "465adedf-48aa-4dc0-a250-a060c3946711",
                "position": 45,
                "resource_type": "file",
                "size": null,
                "state": "active",
                "url": "https://www.ons.gov.uk/releases/gdpfirstquarterlyestimateukjulytoseptember",
                "url_type": null
            }
        ],
        "tags": [],
        "groups": [],
        "relationships_as_subject": [],
        "relationships_as_object": []
    }
}