{
    "help": "https://ckan.publishing.service.gov.uk/api/3/action/help_show?name=package_show",
    "success": true,
    "result": {
        "creator_user_id": "60e687bf-a6d8-43e2-a50e-efab84b27952",
        "id": "06798287-bb74-4f2b-af8c-f3f80b60ab71",
        "isopen": true,
        "license_id": "uk-ogl",
        "license_title": "UK Open Government Licence (OGL)",
        "license_url": "https://www.nationalarchives.gov.uk/doc/open-government-licence/version/3/",
        "metadata_created": "2024-07-20T18:01:08.442796",
        "metadata_modified": "2024-10-20T14:00:57.689838",
        "name": "local-transport-plan-consultation-2024",
        "notes": "This information is being published so that can be used for research projects / ransparency, and recognised that the data is both detailed, and requires specialist GIS software for analysis\r\n\r\nBetween 23 November 2023 and 4 February 2024, we held a significant public consultation looking at 10 policies to deliver a more sustainable future for York\u2019s transport. \r\n\r\nThere are ten policy areas which we believe will help us deliver our ambitions for transport:\r\n\r\n1.\tAccessibility - so that everyone can access the areas and facilities they need and want\r\n\r\n2.\tImproving walking, wheeling and cycling - so that these become real alternatives to driving a car\r\n\r\n3.\tShaping healthy places - offering a range of ways to move around and using the opportunity to provide better places for us to live, work and visit\r\n\r\n4.\tImproving public transport \u2013 upgrading and improving our bus and rail services\r\n\r\n5.\tSafeguarding the environment by cutting carbon, air pollution and noise - meeting climate change targets and improving the health of the city\r\n\r\n6.\tCreate a Movement and Place plan - creating safe, connected transport networks for residents, businesses and visitors\r\n\r\n7.\tReduce car dependency- supporting people to change how they travel, and encourage those who can, to reduce their journeys by car\r\n\r\n8.\tImproving freight and logistics - creating efficient access for businesses while reducing the impact of heavy vehicles\r\n\r\n9.\tEffective maintenance and enforcement - so that people choosing sustainable travel are safe, and that cycling, walking and wheeling routes are well maintained\r\n\r\n10.\tMonitoring the transport network and financing the changes - to ensure the effectiveness of our policies and attract funding to deliver York's new transport strategy as effectively as possible\r\n\r\nThis was to help prepare a new Local Transport Plan by summer 2024. This consultation will help us write a plan and pave the way to work with the new mayor of the incoming York and North Yorkshire Combined Authority. Once our plan is complete, we will then put our case to government and seek funding for the improvements we want to make in the decades to come.\r\n\r\nThe consultation closed on 4 February 2024.\r\n\r\nFor more information on this consultation please click on the link below: \r\n\r\nhttps://www.york.gov.uk/BigTransportConversation \r\n\r\n",
        "num_resources": 18,
        "num_tags": 0,
        "organization": {
            "id": "21f3491f-5b0f-4395-8bb9-990f9cc4d274",
            "name": "city-of-york-council",
            "title": "City of York Council",
            "type": "organization",
            "description": "Corporate Open Data platform - http://www.yorkopendata.org/\r\n\r\nCorporate map browser - http://maps.york.gov.uk/localviewexternal/sites/lv/",
            "image_url": "",
            "created": "2013-11-25T13:21:35.161579",
            "is_organization": true,
            "approval_status": "pending",
            "state": "active"
        },
        "owner_org": "21f3491f-5b0f-4395-8bb9-990f9cc4d274",
        "private": false,
        "state": "active",
        "title": "Local Transport Plan Consultation 2024",
        "type": "dataset",
        "url": "",
        "version": "",
        "resources": [
            {
                "cache_last_updated": null,
                "cache_url": null,
                "created": "2024-05-16T11:02:28.837783",
                "datastore_active": false,
                "description": "Shapefile for Policy idea 1.1 Blue Badge Parking",
                "format": "SHP",
                "hash": "",
                "id": "3bec3922-6b21-4c2b-930d-cf4b4ec4467e",
                "last_modified": "2024-05-16T11:02:28.808722",
                "metadata_modified": "2024-07-20T18:01:08.423393",
                "mimetype": null,
                "mimetype_inner": null,
                "name": "Blue Badge Parking",
                "package_id": "06798287-bb74-4f2b-af8c-f3f80b60ab71",
                "position": 0,
                "resource_type": null,
                "size": null,
                "state": "active",
                "url": "https://data.yorkopendata.org/dataset/06798287-bb74-4f2b-af8c-f3f80b60ab71/resource/3bec3922-6b21-4c2b-930d-cf4b4ec4467e/download/bluebadgeparking_point.zip",
                "url_type": null
            },
            {
                "cache_last_updated": null,
                "cache_url": null,
                "created": "2024-05-16T11:08:40.013702",
                "datastore_active": false,
                "description": "Shapefile for Policy idea 1.2 Cycle Parking",
                "format": "SHP",
                "hash": "",
                "id": "a7d91c2c-fae5-4afc-82ef-5d88c280799a",
                "last_modified": "2024-05-16T11:08:39.873099",
                "metadata_modified": "2024-07-20T18:01:08.424542",
                "mimetype": null,
                "mimetype_inner": null,
                "name": "Cycle Parking",
                "package_id": "06798287-bb74-4f2b-af8c-f3f80b60ab71",
                "position": 1,
                "resource_type": null,
                "size": null,
                "state": "active",
                "url": "https://data.yorkopendata.org/dataset/06798287-bb74-4f2b-af8c-f3f80b60ab71/resource/a7d91c2c-fae5-4afc-82ef-5d88c280799a/download/cycleparking_point.zip",
                "url_type": null
            },
            {
                "cache_last_updated": null,
                "cache_url": null,
                "created": "2024-05-16T11:11:00.659135",
                "datastore_active": false,
                "description": "Shapefile for Policy idea 1.3 Accessible Design",
                "format": "SHP",
                "hash": "",
                "id": "b1f0c9a9-9d96-4609-899a-824c4878ab99",
                "last_modified": "2024-05-16T11:11:00.627087",
                "metadata_modified": "2024-07-20T18:01:08.425661",
                "mimetype": null,
                "mimetype_inner": null,
                "name": "Accessible Design",
                "package_id": "06798287-bb74-4f2b-af8c-f3f80b60ab71",
                "position": 2,
                "resource_type": null,
                "size": null,
                "state": "active",
                "url": "https://data.yorkopendata.org/dataset/06798287-bb74-4f2b-af8c-f3f80b60ab71/resource/b1f0c9a9-9d96-4609-899a-824c4878ab99/download/accessibledesign_point.zip",
                "url_type": null
            },
            {
                "cache_last_updated": null,
                "cache_url": null,
                "created": "2024-05-16T11:13:02.581890",
                "datastore_active": false,
                "description": "Shapefile for Policy idea 1.5 Seating",
                "format": "SHP",
                "hash": "",
                "id": "0d448338-5ac0-4c53-b00a-f764a32c58dc",
                "last_modified": "2024-05-16T11:13:02.548280",
                "metadata_modified": "2024-07-20T18:01:08.426749",
                "mimetype": null,
                "mimetype_inner": null,
                "name": "Seating",
                "package_id": "06798287-bb74-4f2b-af8c-f3f80b60ab71",
                "position": 3,
                "resource_type": null,
                "size": null,
                "state": "active",
                "url": "https://data.yorkopendata.org/dataset/06798287-bb74-4f2b-af8c-f3f80b60ab71/resource/0d448338-5ac0-4c53-b00a-f764a32c58dc/download/seating_point.zip",
                "url_type": null
            },
            {
                "cache_last_updated": null,
                "cache_url": null,
                "created": "2024-05-16T11:15:19.162026",
                "datastore_active": false,
                "description": "Shapefile for Policy idea 2.2 Walking and Wheeling Network",
                "format": "SHP",
                "hash": "",
                "id": "dddbd93e-4363-426d-b7c7-e91b8af0c3b3",
                "last_modified": "2024-05-16T11:15:19.123240",
                "metadata_modified": "2024-07-20T18:01:08.427823",
                "mimetype": null,
                "mimetype_inner": null,
                "name": "Walking and Wheeling Network",
                "package_id": "06798287-bb74-4f2b-af8c-f3f80b60ab71",
                "position": 4,
                "resource_type": null,
                "size": null,
                "state": "active",
                "url": "https://data.yorkopendata.org/dataset/06798287-bb74-4f2b-af8c-f3f80b60ab71/resource/dddbd93e-4363-426d-b7c7-e91b8af0c3b3/download/walkingandwheeling_polyline.zip",
                "url_type": null
            },
            {
                "cache_last_updated": null,
                "cache_url": null,
                "created": "2024-05-16T11:16:47.338682",
                "datastore_active": false,
                "description": "Shapefile for Policy idea 2.3 Pedestrian Crossing (Barriers)",
                "format": "SHP",
                "hash": "",
                "id": "30465ad5-6784-43f8-b551-59c1b0360f44",
                "last_modified": "2024-05-16T11:16:47.300245",
                "metadata_modified": "2024-07-20T18:01:08.428881",
                "mimetype": null,
                "mimetype_inner": null,
                "name": "Pedestrian Crossing (Barriers)",
                "package_id": "06798287-bb74-4f2b-af8c-f3f80b60ab71",
                "position": 5,
                "resource_type": null,
                "size": null,
                "state": "active",
                "url": "https://data.yorkopendata.org/dataset/06798287-bb74-4f2b-af8c-f3f80b60ab71/resource/30465ad5-6784-43f8-b551-59c1b0360f44/download/pedestriancrossingbarriers_point.zip",
                "url_type": null
            },
            {
                "cache_last_updated": null,
                "cache_url": null,
                "created": "2024-05-16T11:19:08.699857",
                "datastore_active": false,
                "description": "Shapefile for Policy idea 2.3 Pedestrian Crossing (Condition)",
                "format": "SHP",
                "hash": "",
                "id": "3503353b-2839-4913-84b5-917eb62e5069",
                "last_modified": "2024-05-16T11:19:08.658003",
                "metadata_modified": "2024-07-20T18:01:08.429952",
                "mimetype": null,
                "mimetype_inner": null,
                "name": "Pedestrian Crossing (Condition)",
                "package_id": "06798287-bb74-4f2b-af8c-f3f80b60ab71",
                "position": 6,
                "resource_type": null,
                "size": null,
                "state": "active",
                "url": "https://data.yorkopendata.org/dataset/06798287-bb74-4f2b-af8c-f3f80b60ab71/resource/3503353b-2839-4913-84b5-917eb62e5069/download/pedestriancrossingcondition_point.zip",
                "url_type": null
            },
            {
                "cache_last_updated": null,
                "cache_url": null,
                "created": "2024-05-16T11:21:12.330346",
                "datastore_active": false,
                "description": "Shapefile for Policy idea 2.3 Pedestrian Crossing (Priority)",
                "format": "SHP",
                "hash": "",
                "id": "91ce3cc7-2698-4a17-9f23-8bb30da3cfdb",
                "last_modified": "2024-05-16T11:21:12.286124",
                "metadata_modified": "2024-07-20T18:01:08.431042",
                "mimetype": null,
                "mimetype_inner": null,
                "name": "Pedestrian Crossing (Priority)",
                "package_id": "06798287-bb74-4f2b-af8c-f3f80b60ab71",
                "position": 7,
                "resource_type": null,
                "size": null,
                "state": "active",
                "url": "https://data.yorkopendata.org/dataset/06798287-bb74-4f2b-af8c-f3f80b60ab71/resource/91ce3cc7-2698-4a17-9f23-8bb30da3cfdb/download/pedestriancrossingpriority_point.zip",
                "url_type": null
            },
            {
                "cache_last_updated": null,
                "cache_url": null,
                "created": "2024-05-16T11:23:03.234303",
                "datastore_active": false,
                "description": "Shapefile for Policy idea 2.4 Footstreets Condition",
                "format": "SHP",
                "hash": "",
                "id": "71e34cec-bd2f-41f2-998a-1f6e439ec735",
                "last_modified": "2024-05-16T11:23:03.191985",
                "metadata_modified": "2024-07-20T18:01:08.432109",
                "mimetype": null,
                "mimetype_inner": null,
                "name": "Footpath Condition",
                "package_id": "06798287-bb74-4f2b-af8c-f3f80b60ab71",
                "position": 8,
                "resource_type": null,
                "size": null,
                "state": "active",
                "url": "https://data.yorkopendata.org/dataset/06798287-bb74-4f2b-af8c-f3f80b60ab71/resource/71e34cec-bd2f-41f2-998a-1f6e439ec735/download/footpathcondition_point.zip",
                "url_type": null
            },
            {
                "cache_last_updated": null,
                "cache_url": null,
                "created": "2024-05-16T11:25:19.797952",
                "datastore_active": false,
                "description": "Shapefile for Policy idea 2.5 Cycle Network ",
                "format": "SHP",
                "hash": "",
                "id": "3262f7e7-7c48-45df-9639-b7eb7e55be67",
                "last_modified": "2024-05-16T11:25:19.752899",
                "metadata_modified": "2024-07-20T18:01:08.433173",
                "mimetype": null,
                "mimetype_inner": null,
                "name": "Cycle Network",
                "package_id": "06798287-bb74-4f2b-af8c-f3f80b60ab71",
                "position": 9,
                "resource_type": null,
                "size": null,
                "state": "active",
                "url": "https://data.yorkopendata.org/dataset/06798287-bb74-4f2b-af8c-f3f80b60ab71/resource/3262f7e7-7c48-45df-9639-b7eb7e55be67/download/cyclenetwork_polyline.zip",
                "url_type": null
            },
            {
                "cache_last_updated": null,
                "cache_url": null,
                "created": "2024-05-16T12:42:53.783226",
                "datastore_active": false,
                "description": "Shapefile for Policy idea 5.1 Electric Vehicle Charging (Locations)",
                "format": "SHP",
                "hash": "",
                "id": "da678e3b-fa98-4a17-99d5-144aa71eca0a",
                "last_modified": "2024-05-16T12:42:53.736391",
                "metadata_modified": "2024-07-20T18:01:08.434276",
                "mimetype": null,
                "mimetype_inner": null,
                "name": "Electric Vehicle Charging (Locations)",
                "package_id": "06798287-bb74-4f2b-af8c-f3f80b60ab71",
                "position": 10,
                "resource_type": null,
                "size": null,
                "state": "active",
                "url": "https://data.yorkopendata.org/dataset/06798287-bb74-4f2b-af8c-f3f80b60ab71/resource/da678e3b-fa98-4a17-99d5-144aa71eca0a/download/evchargepoints_point.zip",
                "url_type": null
            },
            {
                "cache_last_updated": null,
                "cache_url": null,
                "created": "2024-05-16T12:45:40.652352",
                "datastore_active": false,
                "description": "Shapefile for Policy idea 5.3 Bus Clean Air Zone",
                "format": "SHP",
                "hash": "",
                "id": "9d9e8aaa-8cfc-4a10-b763-815efb925f43",
                "last_modified": "2024-05-16T12:45:40.417990",
                "metadata_modified": "2024-07-20T18:01:08.435395",
                "mimetype": null,
                "mimetype_inner": null,
                "name": "Bus Clean Air Zone",
                "package_id": "06798287-bb74-4f2b-af8c-f3f80b60ab71",
                "position": 11,
                "resource_type": null,
                "size": null,
                "state": "active",
                "url": "https://data.yorkopendata.org/dataset/06798287-bb74-4f2b-af8c-f3f80b60ab71/resource/9d9e8aaa-8cfc-4a10-b763-815efb925f43/download/buscleanairzone_point.zip",
                "url_type": null
            },
            {
                "cache_last_updated": null,
                "cache_url": null,
                "created": "2024-05-16T12:47:08.540158",
                "datastore_active": false,
                "description": "Shapefile for Policy idea 6.2 Movement and Place Opportunities",
                "format": "SHP",
                "hash": "",
                "id": "57e74634-c17e-42ee-9a3e-5d11d3be70e0",
                "last_modified": "2024-05-16T12:47:08.487920",
                "metadata_modified": "2024-07-20T18:01:08.436479",
                "mimetype": null,
                "mimetype_inner": null,
                "name": "Movement and Place Opportunities",
                "package_id": "06798287-bb74-4f2b-af8c-f3f80b60ab71",
                "position": 12,
                "resource_type": null,
                "size": null,
                "state": "active",
                "url": "https://data.yorkopendata.org/dataset/06798287-bb74-4f2b-af8c-f3f80b60ab71/resource/57e74634-c17e-42ee-9a3e-5d11d3be70e0/download/movementandplace_point.zip",
                "url_type": null
            },
            {
                "cache_last_updated": null,
                "cache_url": null,
                "created": "2024-05-16T12:51:27.459358",
                "datastore_active": false,
                "description": "Shapefile for Policy idea 9.1 Pavement Maintenance",
                "format": "SHP",
                "hash": "",
                "id": "8272db2e-6765-4d17-a752-fb1a72af26ec",
                "last_modified": "2024-05-16T12:51:27.407440",
                "metadata_modified": "2024-07-20T18:01:08.437561",
                "mimetype": null,
                "mimetype_inner": null,
                "name": "Pavement Maintenance",
                "package_id": "06798287-bb74-4f2b-af8c-f3f80b60ab71",
                "position": 13,
                "resource_type": null,
                "size": null,
                "state": "active",
                "url": "https://data.yorkopendata.org/dataset/06798287-bb74-4f2b-af8c-f3f80b60ab71/resource/8272db2e-6765-4d17-a752-fb1a72af26ec/download/pavementmaintenance_point.zip",
                "url_type": null
            },
            {
                "cache_last_updated": null,
                "cache_url": null,
                "created": "2024-05-16T12:55:52.791407",
                "datastore_active": false,
                "description": "Shapefile for Policy idea 9.2 Traffic Enforcement",
                "format": "SHP",
                "hash": "",
                "id": "711df22a-7f30-4efb-8f13-a53dc8c82045",
                "last_modified": "2024-05-16T12:55:52.737537",
                "metadata_modified": "2024-07-20T18:01:08.438645",
                "mimetype": null,
                "mimetype_inner": null,
                "name": "Traffic Enforcement",
                "package_id": "06798287-bb74-4f2b-af8c-f3f80b60ab71",
                "position": 14,
                "resource_type": null,
                "size": null,
                "state": "active",
                "url": "https://data.yorkopendata.org/dataset/06798287-bb74-4f2b-af8c-f3f80b60ab71/resource/711df22a-7f30-4efb-8f13-a53dc8c82045/download/trafficenforcementareas_point.zip",
                "url_type": null
            },
            {
                "cache_last_updated": null,
                "cache_url": null,
                "created": "2024-05-17T07:36:11.684832",
                "datastore_active": true,
                "description": "Question set for Our Big Transport Conversation 23-24",
                "format": "XLSX",
                "hash": "",
                "id": "29990cfa-b7fb-47ed-924d-150ef8e2cb84",
                "last_modified": "2024-05-17T07:36:11.622381",
                "metadata_modified": "2024-07-20T18:01:08.439719",
                "mimetype": null,
                "mimetype_inner": null,
                "name": "Our Big Transport Conversation 23-24 - Questions",
                "package_id": "06798287-bb74-4f2b-af8c-f3f80b60ab71",
                "position": 15,
                "resource_type": null,
                "size": null,
                "state": "active",
                "url": "https://data.yorkopendata.org/dataset/06798287-bb74-4f2b-af8c-f3f80b60ab71/resource/29990cfa-b7fb-47ed-924d-150ef8e2cb84/download/our-big-transport-conversation-23-24-questions-.xlsx",
                "url_type": null
            },
            {
                "cache_last_updated": null,
                "cache_url": null,
                "created": "2024-05-17T07:39:10.828015",
                "datastore_active": false,
                "description": "Responses for Our Big Transport Conversation 23-24",
                "format": "XLSX",
                "hash": "",
                "id": "2cdf7686-0c16-4455-822c-9ee33eacdd0f",
                "last_modified": "2024-05-17T07:39:10.771163",
                "metadata_modified": "2024-07-20T18:01:08.440793",
                "mimetype": null,
                "mimetype_inner": null,
                "name": "Our Big Transport Conversation 23-24 - Responses",
                "package_id": "06798287-bb74-4f2b-af8c-f3f80b60ab71",
                "position": 16,
                "resource_type": null,
                "size": null,
                "state": "active",
                "url": "https://data.yorkopendata.org/dataset/06798287-bb74-4f2b-af8c-f3f80b60ab71/resource/2cdf7686-0c16-4455-822c-9ee33eacdd0f/download/our-big-transport-conversation-23-24-responses.xlsx",
                "url_type": null
            },
            {
                "cache_last_updated": null,
                "cache_url": null,
                "created": "2024-10-15T08:32:55.831526",
                "datastore_active": false,
                "description": "Results by Ward for Our Big Transport Conversation 23-24",
                "format": "PDF",
                "hash": "",
                "id": "7118f983-f47c-4f35-a4e5-c533cfdd1127",
                "last_modified": "2024-10-15T08:32:55.759045",
                "metadata_modified": "2024-10-20T14:00:57.697405",
                "mimetype": null,
                "mimetype_inner": null,
                "name": "Our Big Transport Conversation - Results by Ward",
                "package_id": "06798287-bb74-4f2b-af8c-f3f80b60ab71",
                "position": 17,
                "resource_type": null,
                "size": null,
                "state": "active",
                "url": "https://data.yorkopendata.org/dataset/06798287-bb74-4f2b-af8c-f3f80b60ab71/resource/7118f983-f47c-4f35-a4e5-c533cfdd1127/download/ltp-results-by-ward-2024.pdf",
                "url_type": null
            }
        ],
        "tags": [],
        "extras": [
            {
                "key": "harvest_object_id",
                "value": "30171024-c993-4c08-b32d-57c0310fd5fa"
            },
            {
                "key": "harvest_source_id",
                "value": "4ec45354-b7dc-48c1-a22f-c5938e88695b"
            },
            {
                "key": "harvest_source_title",
                "value": "York Open Data"
            }
        ],
        "groups": [],
        "relationships_as_subject": [],
        "relationships_as_object": [],
        "harvest": [
            {
                "key": "harvest_object_id",
                "value": "30171024-c993-4c08-b32d-57c0310fd5fa"
            },
            {
                "key": "harvest_source_id",
                "value": "4ec45354-b7dc-48c1-a22f-c5938e88695b"
            },
            {
                "key": "harvest_source_title",
                "value": "York Open Data"
            }
        ]
    }
}