{
    "help": "https://ckan.publishing.service.gov.uk/api/3/action/help_show?name=package_show",
    "success": true,
    "result": {
        "creator_user_id": "ab19a913-1fd8-4ec6-9595-cb579a9fd0b2",
        "date_released": "2009-09-22",
        "date_updated": "2014-07-10",
        "geographic_coverage": "000100: Northern Ireland",
        "geographic_granularity": "Country",
        "id": "b3d0ad17-4df6-47e6-bdf3-9ffaf49e2ad5",
        "isopen": true,
        "license_id": "uk-ogl",
        "license_title": "UK Open Government Licence (OGL)",
        "license_url": "http://reference.data.gov.uk/id/open-government-licence",
        "metadata_created": "2011-12-11T03:37:49.965208",
        "metadata_modified": "2016-01-26T11:59:22.159784",
        "name": "travel_survey_for_northern_ireland",
        "notes": "The publication contains information on journeys taken by Northern Ireland residents by mode of travel and purpose of journey.\n\nSource agency: Regional Development (Northern Ireland)\n\nDesignation: National Statistics\n\nLanguage: English\n\nAlternative title: Travel Survey for Northern Ireland",
        "num_resources": 10,
        "num_tags": 0,
        "odi-certificate": {
            "status": "final",
            "source": "Automatically awarded by ODI",
            "certification_type": "automatically awarded",
            "level": "bronze",
            "title": "Travel Survey for Northern Ireland",
            "created_at": "2014-10-29T16:28:32Z",
            "jurisdiction": "GB",
            "certificate_url": "https://certificates.theodi.org/en/datasets/10684/certificate",
            "badge_url": "https://certificates.theodi.org/en/datasets/10684/certificate/badge.png",
            "cert_title": "Bronze level certificate"
        },
        "organization": {
            "id": "adabb261-9fa4-428c-ab71-db8e821601be",
            "name": "department-for-regional-development",
            "title": "Department for Regional Development",
            "type": "organization",
            "description": "",
            "image_url": "",
            "created": "2012-06-27T14:54:10.872020",
            "is_organization": true,
            "approval_status": "approved",
            "state": "active"
        },
        "owner_org": "adabb261-9fa4-428c-ab71-db8e821601be",
        "precision": "",
        "private": false,
        "state": "active",
        "temporal_coverage-from": "",
        "temporal_coverage-to": "",
        "temporal_granularity": "",
        "theme-primary": "transport",
        "title": "Travel Survey for Northern Ireland",
        "type": "dataset",
        "update_frequency": "",
        "url": null,
        "version": null,
        "extras": [
            {
                "key": "categories",
                "value": "Travel and Transport"
            },
            {
                "key": "external_reference",
                "value": "ONSHUB"
            },
            {
                "key": "geographical_granularity",
                "value": "Country"
            },
            {
                "key": "import_source",
                "value": "ONS-ons_data_1_days_to_2014-07-10"
            },
            {
                "key": "last_major_modification",
                "value": "2013-12-19T10:27:40.514506"
            },
            {
                "key": "national_statistic",
                "value": "yes"
            },
            {
                "key": "provider",
                "value": "Northern Ireland Executive"
            },
            {
                "key": "series",
                "value": "Travel Survey for Northern Ireland"
            }
        ],
        "resources": [
            {
                "cache_last_updated": null,
                "cache_url": null,
                "created": "2013-03-11T17:40:04.201572",
                "description": "Travel Survey for Northern Ireland 2006-2008",
                "format": "HTML",
                "hub-id": "119-40090",
                "id": "be998bee-cd06-46be-8cf7-0a0baf8092bc",
                "last_modified": null,
                "metadata_modified": "2013-03-11T17:40:04.201572",
                "mimetype": null,
                "mimetype_inner": null,
                "name": null,
                "package_id": "b3d0ad17-4df6-47e6-bdf3-9ffaf49e2ad5",
                "position": 0,
                "publish-date": "2009-09-22",
                "resource_type": "file",
                "size": null,
                "state": "active",
                "url": "http://webarchive.nationalarchives.gov.uk/+/http://www.drdni.gov.uk/index/statistics/stats-catagories.htm",
                "url_type": null
            },
            {
                "cache_last_updated": null,
                "cache_url": null,
                "created": "2013-03-11T20:38:41.893600",
                "description": "2007-2009 Headline Figures Report",
                "format": "HTML",
                "hub-id": "119-46468",
                "id": "a5e86cc8-c9db-4cdf-9050-a1a252728f48",
                "last_modified": null,
                "metadata_modified": "2013-03-11T20:38:41.893600",
                "mimetype": null,
                "mimetype_inner": null,
                "name": null,
                "package_id": "b3d0ad17-4df6-47e6-bdf3-9ffaf49e2ad5",
                "position": 1,
                "publish-date": "2010-06-30",
                "resource_type": "file",
                "size": null,
                "state": "active",
                "url": "http://webarchive.nationalarchives.gov.uk/+/http://www.drdni.gov.uk/index/statistics/stats-catagories/stats-catagories-travel_survey.htm",
                "url_type": null
            },
            {
                "cache_last_updated": null,
                "cache_url": null,
                "created": "2013-03-11T22:47:11.844956",
                "description": "2007-2009 In Depth Report",
                "format": "HTML",
                "hub-id": "119-49799",
                "id": "a9368f66-aea6-44b0-bea2-38663fb0cf18",
                "last_modified": null,
                "metadata_modified": "2013-03-11T22:47:11.844956",
                "mimetype": null,
                "mimetype_inner": null,
                "name": null,
                "package_id": "b3d0ad17-4df6-47e6-bdf3-9ffaf49e2ad5",
                "position": 2,
                "publish-date": "2011-01-06",
                "resource_type": "file",
                "size": null,
                "state": "active",
                "url": "http://webarchive.nationalarchives.gov.uk/+/http://www.drdni.gov.uk/index/statistics/stats-catagories/stats-catagories-travel_survey.htm",
                "url_type": null
            },
            {
                "cache_last_updated": null,
                "cache_url": null,
                "created": "2013-03-12T00:45:19.719632",
                "description": "Headline Figures Report 2008-2010",
                "format": "HTML",
                "hub-id": "119-51171",
                "id": "1e3c0840-9feb-4c27-94cf-88595b5ba9c6",
                "last_modified": null,
                "metadata_modified": "2013-03-12T00:45:19.719632",
                "mimetype": null,
                "mimetype_inner": null,
                "name": null,
                "package_id": "b3d0ad17-4df6-47e6-bdf3-9ffaf49e2ad5",
                "position": 3,
                "publish-date": "2011-06-30",
                "resource_type": "file",
                "size": null,
                "state": "active",
                "url": "http://webarchive.nationalarchives.gov.uk/+/http://www.drdni.gov.uk/index/statistics/stats-catagories/stats-catagories-travel_survey.htm",
                "url_type": null
            },
            {
                "cache_last_updated": null,
                "cache_url": null,
                "created": "2013-03-12T03:04:52.847103",
                "description": "In-depth Report 2008-2010",
                "format": "HTML",
                "hub-id": "119-51173",
                "id": "84b9cf67-afe6-466b-993b-a9abe1217530",
                "last_modified": null,
                "metadata_modified": "2013-03-12T03:04:52.847103",
                "mimetype": null,
                "mimetype_inner": null,
                "name": null,
                "package_id": "b3d0ad17-4df6-47e6-bdf3-9ffaf49e2ad5",
                "position": 4,
                "publish-date": "2011-12-22",
                "resource_type": "file",
                "size": null,
                "state": "active",
                "url": "http://webarchive.nationalarchives.gov.uk/+/http://www.drdni.gov.uk/index/statistics/stats-catagories/stats-catagories-travel_survey.htm",
                "url_type": null
            },
            {
                "cache_last_updated": null,
                "cache_url": null,
                "created": "2013-10-01T02:05:02.265995",
                "description": "Headline Report 2009-2011",
                "format": "HTML",
                "hub-id": "119-57389",
                "id": "5b334306-7550-46f0-a070-738612dbfbd9",
                "last_modified": null,
                "metadata_modified": "2013-10-01T02:05:02.265995",
                "mimetype": null,
                "mimetype_inner": null,
                "name": null,
                "package_id": "b3d0ad17-4df6-47e6-bdf3-9ffaf49e2ad5",
                "position": 5,
                "publish-date": "2012-07-05",
                "resource_type": "file",
                "size": null,
                "state": "active",
                "url": "http://webarchive.nationalarchives.gov.uk/+/http://www.drdni.gov.uk/index/statistics/stats-catagories/stats-catagories-travel_survey.htm",
                "url_type": null
            },
            {
                "cache_last_updated": null,
                "cache_url": null,
                "created": "2013-10-01T03:09:35.886714",
                "description": "In-Depth Report 2009-2011",
                "format": "HTML",
                "hub-id": "119-57393",
                "id": "3bf50107-5dd0-423c-a4fd-0042626a7da0",
                "last_modified": null,
                "metadata_modified": "2013-10-01T03:09:35.886714",
                "mimetype": null,
                "mimetype_inner": null,
                "name": null,
                "package_id": "b3d0ad17-4df6-47e6-bdf3-9ffaf49e2ad5",
                "position": 6,
                "publish-date": "2012-12-20",
                "resource_type": "file",
                "size": null,
                "state": "active",
                "url": "http://webarchive.nationalarchives.gov.uk/+/http://www.drdni.gov.uk/index/statistics/stats-catagories/stats-catagories-travel_survey.htm",
                "url_type": null
            },
            {
                "cache_last_updated": null,
                "cache_url": null,
                "created": "2013-10-01T04:21:56.048781",
                "description": "Headline Report 2010-2012",
                "format": "HTML",
                "hub-id": "119-66136",
                "id": "83246ab9-e246-49ce-a34a-8945c98eecbf",
                "last_modified": null,
                "metadata_modified": "2013-10-01T04:21:56.048781",
                "mimetype": null,
                "mimetype_inner": null,
                "name": null,
                "package_id": "b3d0ad17-4df6-47e6-bdf3-9ffaf49e2ad5",
                "position": 7,
                "publish-date": "2013-07-25",
                "resource_type": "file",
                "size": null,
                "state": "active",
                "url": "http://www.drdni.gov.uk/index/statistics/stats-categories/northern_ireland_travel_survey.htm",
                "url_type": null
            },
            {
                "cache_last_updated": null,
                "cache_url": null,
                "created": "2013-12-19T10:27:40.864828",
                "description": "In-Depth Report 2010-2012",
                "format": "HTML",
                "hub-id": "119-70357",
                "id": "c52b3b92-dbf7-472d-8e60-ed6fbfcf7ffc",
                "last_modified": null,
                "metadata_modified": "2013-12-19T10:27:40.864828",
                "mimetype": null,
                "mimetype_inner": null,
                "name": null,
                "package_id": "b3d0ad17-4df6-47e6-bdf3-9ffaf49e2ad5",
                "position": 8,
                "publish-date": "2013-12-19",
                "resource_type": "file",
                "size": null,
                "state": "active",
                "url": "http://www.drdni.gov.uk/index/statistics/stats-categories/northern_ireland_travel_survey.htm",
                "url_type": null
            },
            {
                "cache_last_updated": null,
                "cache_url": null,
                "created": "2014-07-10T09:40:16.464786",
                "description": "Headline Report 2011-2013",
                "format": "HTML",
                "hash": "",
                "hub-id": "119-74324",
                "id": "9fb74c36-30b0-4a4e-9082-ccb4552458e9",
                "last_modified": null,
                "metadata_modified": "2014-07-10T09:40:16.464786",
                "mimetype": null,
                "mimetype_inner": null,
                "name": null,
                "package_id": "b3d0ad17-4df6-47e6-bdf3-9ffaf49e2ad5",
                "position": 9,
                "publish-date": "2014-07-10",
                "resource_type": "file",
                "size": null,
                "state": "active",
                "url": "http://www.drdni.gov.uk/index/statistics/stats-categories/northern_ireland_travel_survey.htm",
                "url_type": null
            }
        ],
        "tags": [],
        "groups": [],
        "relationships_as_subject": [],
        "relationships_as_object": []
    }
}